<?xml version="1.0"?>
<graph name="GliderConverter">
  <factions ids="189" />
  <mines all="False" />
  <herbs all="False" />
  <hotspots count="0" />
  <nodes count="63">
    <node id="0" x="-6180" y="545,16" z="0" />
    <node id="1" x="-6171,06" y="557,12" z="0" />
    <node id="2" x="-6168,34" y="570,06" z="0" />
    <node id="3" x="-6156,48" y="569,67" z="0" />
    <node id="4" x="-6144,41" y="566,43" z="0" />
    <node id="5" x="-6135,25" y="556,06" z="0" />
    <node id="6" x="-6127,86" y="565,16" z="0" />
    <node id="7" x="-6139,12" y="571,19" z="0" />
    <node id="8" x="-6135,82" y="583,27" z="0" />
    <node id="9" x="-6130,29" y="595,76" z="0" />
    <node id="10" x="-6126,67" y="607,94" z="0" />
    <node id="11" x="-6131,21" y="620,97" z="0" />
    <node id="12" x="-6134,26" y="634,16" z="0" />
    <node id="13" x="-6142,03" y="645,3" z="0" />
    <node id="14" x="-6149,56" y="656,06" z="0" />
    <node id="15" x="-6148,49" y="669,56" z="0" />
    <node id="16" x="-6150,44" y="683,04" z="0" />
    <node id="17" x="-6160,12" y="692,65" z="0" />
    <node id="18" x="-6172,86" y="690,14" z="0" />
    <node id="19" x="-6176,34" y="703,02" z="0" />
    <node id="20" x="-6176,23" y="716,8" z="0" />
    <node id="21" x="-6176,38" y="729,58" z="0" />
    <node id="22" x="-6172,71" y="742,03" z="0" />
    <node id="23" x="-6164,89" y="753,39" z="0" />
    <node id="24" x="-6158,45" y="765,14" z="0" />
    <node id="25" x="-6159,29" y="777,41" z="0" />
    <node id="26" x="-6170,2" y="785,06" z="0" />
    <node id="27" x="-6183,47" y="786,05" z="0" />
    <node id="28" x="-6194,98" y="779,3" z="0" />
    <node id="29" x="-6202,97" y="770,04" z="0" />
    <node id="30" x="-6203,64" y="756,4" z="0" />
    <node id="31" x="-6208,46" y="743,61" z="0" />
    <node id="32" x="-6213,82" y="730,95" z="0" />
    <node id="33" x="-6225,15" y="731,56" z="0" />
    <node id="34" x="-6236,92" y="739,07" z="0" />
    <node id="35" x="-6244,77" y="748,94" z="0" />
    <node id="36" x="-6250,63" y="760,31" z="0" />
    <node id="37" x="-6263,07" y="765,42" z="0" />
    <node id="38" x="-6272,15" y="755,12" z="0" />
    <node id="39" x="-6278,12" y="743,15" z="0" />
    <node id="40" x="-6282,51" y="730,73" z="0" />
    <node id="41" x="-6277,59" y="717,99" z="0" />
    <node id="42" x="-6273,34" y="704,63" z="0" />
    <node id="43" x="-6267,07" y="691,52" z="0" />
    <node id="44" x="-6254" y="689,06" z="0" />
    <node id="45" x="-6241,82" y="695,6" z="0" />
    <node id="46" x="-6232,27" y="704,48" z="0" />
    <node id="47" x="-6218,9" y="708,3" z="0" />
    <node id="48" x="-6207,15" y="703,43" z="0" />
    <node id="49" x="-6204,22" y="690,92" z="0" />
    <node id="50" x="-6194,52" y="681,6" z="0" />
    <node id="51" x="-6182,46" y="675,12" z="0" />
    <node id="52" x="-6172,73" y="665,99" z="0" />
    <node id="53" x="-6171,72" y="652,04" z="0" />
    <node id="54" x="-6164,41" y="642,87" z="0" />
    <node id="55" x="-6154,89" y="633,9" z="0" />
    <node id="56" x="-6148,94" y="622,02" z="0" />
    <node id="57" x="-6154,18" y="609,85" z="0" />
    <node id="58" x="-6159,04" y="597,85" z="0" />
    <node id="59" x="-6156,64" y="584,55" z="0" />
    <node id="60" x="-6159,93" y="571,81" z="0" />
    <node id="61" x="-6170,77" y="565,9" z="0" />
    <node id="62" x="-6177,52" y="552,36" z="0" />
  </nodes>
  <nodesSell count="0" />
  <nodesDeath count="0" />
</graph>