<?xml version="1.0"?>
<graph name="GliderConverter">
  <factions ids="99999" />
  <mines all="False" />
  <herbs all="False" />
  <hotspots count="0" />
  <nodes count="45">
    <node id="0" x="-941,51" y="-185,98" z="0" />
    <node id="1" x="-952,77" y="-172,75" z="0" />
    <node id="2" x="-950,31" y="-169,45" z="0" />
    <node id="3" x="-948,55" y="-153,49" z="0" />
    <node id="4" x="-943,85" y="-140,65" z="0" />
    <node id="5" x="-941,93" y="-123,49" z="0" />
    <node id="6" x="-948,06" y="-109,94" z="0" />
    <node id="7" x="-957,45" y="-100,08" z="0" />
    <node id="8" x="-966,78" y="-89,85" z="0" />
    <node id="9" x="-966,2" y="-76,81" z="0" />
    <node id="10" x="-959,11" y="-64,5" z="0" />
    <node id="11" x="-948,1" y="-55,95" z="0" />
    <node id="12" x="-934,42" y="-50,07" z="0" />
    <node id="13" x="-924,03" y="-57,96" z="0" />
    <node id="14" x="-909,49" y="-62,16" z="0" />
    <node id="15" x="-896,06" y="-59,99" z="0" />
    <node id="16" x="-882,86" y="-59,46" z="0" />
    <node id="17" x="-873,37" y="-49,73" z="0" />
    <node id="18" x="-868,83" y="-36,79" z="0" />
    <node id="19" x="-864,58" y="-24,01" z="0" />
    <node id="20" x="-860,13" y="-10,64" z="0" />
    <node id="21" x="-860,83" y="-23,77" z="0" />
    <node id="22" x="-870,03" y="-38,78" z="0" />
    <node id="23" x="-876,62" y="-50,35" z="0" />
    <node id="24" x="-889,9" y="-53,97" z="0" />
    <node id="25" x="-903,18" y="-56,93" z="0" />
    <node id="26" x="-916,76" y="-58,46" z="0" />
    <node id="27" x="-908,29" y="-72,08" z="0" />
    <node id="28" x="-903,93" y="-84,76" z="0" />
    <node id="29" x="-897,01" y="-96,64" z="0" />
    <node id="30" x="-898,49" y="-110,34" z="0" />
    <node id="31" x="-899,3" y="-127,56" z="0" />
    <node id="32" x="-905,74" y="-143,63" z="0" />
    <node id="33" x="-900,07" y="-131,78" z="0" />
    <node id="34" x="-896,76" y="-118,36" z="0" />
    <node id="35" x="-899,09" y="-104,7" z="0" />
    <node id="36" x="-900,92" y="-90,99" z="0" />
    <node id="37" x="-905,47" y="-78,19" z="0" />
    <node id="38" x="-906,89" y="-64,7" z="0" />
    <node id="39" x="-891,74" y="-56,9" z="0" />
    <node id="40" x="-878,21" y="-58,92" z="0" />
    <node id="41" x="-864,82" y="-62,36" z="0" />
    <node id="42" x="-851,14" y="-63,98" z="0" />
    <node id="43" x="-837,83" y="-65,49" z="0" />
    <node id="44" x="-852,69" y="-62,46" z="0" />
  </nodes>
  <nodesSell count="0" />
  <nodesDeath count="0" />
</graph>