<?xml version="1.0"?>
<graph name="GliderConverter">
  <factions ids="22,7" />
  <mines all="False" />
  <herbs all="False" />
  <hotspots count="0" />
  <nodes count="24">
    <node id="0" x="2047,52" y="1793,2" z="0" />
    <node id="1" x="2046,91" y="1779,86" z="0" />
    <node id="2" x="2048,17" y="1766,17" z="0" />
    <node id="3" x="2047,7" y="1750,66" z="0" />
    <node id="4" x="2047,04" y="1737,35" z="0" />
    <node id="5" x="2047,58" y="1723,09" z="0" />
    <node id="6" x="2049,68" y="1709,32" z="0" />
    <node id="7" x="2059,59" y="1700,25" z="0" />
    <node id="8" x="2072,29" y="1696" z="0" />
    <node id="9" x="2085,48" y="1692,33" z="0" />
    <node id="10" x="2097,43" y="1687,2" z="0" />
    <node id="11" x="2109,82" y="1682,24" z="0" />
    <node id="12" x="2115,36" y="1692,63" z="0" />
    <node id="13" x="2109,15" y="1704,86" z="0" />
    <node id="14" x="2109,34" y="1718,2" z="0" />
    <node id="15" x="2118,07" y="1727,22" z="0" />
    <node id="16" x="2127,28" y="1737,58" z="0" />
    <node id="17" x="2126,54" y="1750,13" z="0" />
    <node id="18" x="2118,13" y="1760,52" z="0" />
    <node id="19" x="2106,89" y="1760,49" z="0" />
    <node id="20" x="2093,73" y="1762,85" z="0" />
    <node id="21" x="2081,11" y="1768,71" z="0" />
    <node id="22" x="2068,48" y="1772,42" z="0" />
    <node id="23" x="2059,28" y="1782,3" z="0" />
  </nodes>
  <nodesSell count="0" />
  <nodesDeath count="0" />
</graph>